scribes/__init__.py
scribes/cli.py
scribes-0.1.2.dist-info/LICENSE
scribes-0.1.2.dist-info/METADATA
scribes-0.1.2.dist-info/WHEEL
scribes-0.1.2.dist-info/entry_points.txt
scribes-0.1.2.dist-info/RECORD
