Metadata-Version: 2.1
Name: scribes
Version: 0.1.2
Summary: 
Home-page: https://github.com/armand-sauzay/scribes
Author: Armand Sauzay
Author-email: 35524799+armand-sauzay@users.noreply.github.com
Requires-Python: >=3.8
Classifier: Programming Language :: Python :: 3
Classifier: Programming Language :: Python :: 3.8
Classifier: Programming Language :: Python :: 3.9
Classifier: Programming Language :: Python :: 3.10
Classifier: Programming Language :: Python :: 3.11
Classifier: Programming Language :: Python :: 3.12
Requires-Dist: click (==8.1.7)
Requires-Dist: pydantic (==2.8.2)
Project-URL: Repository, https://github.com/armand-sauzay/scribes
